elgin/__init__.py
elgin/monitoramento.py
elgin/templates/template_email_log.html
elgin/templates/template_teams.json
elgin-0.1.11.dist-info/METADATA
elgin-0.1.11.dist-info/WHEEL
elgin-0.1.11.dist-info/top_level.txt
elgin-0.1.11.dist-info/RECORD
